sdk/__init__.py
sdk/agent_protocol_client.py
sdk/agent_sdk.py
sdk/chain_utils.py
sdk/cli.py
sdk/client.py
sdk/contract_adapter.py
sdk/exceptions.py
sdk/retry.py
sdk/signer.py
sdk/utils.py
trc_8004_sdk-0.1.0b1.dist-info/METADATA
trc_8004_sdk-0.1.0b1.dist-info/WHEEL
trc_8004_sdk-0.1.0b1.dist-info/entry_points.txt
trc_8004_sdk-0.1.0b1.dist-info/top_level.txt
trc_8004_sdk-0.1.0b1.dist-info/RECORD
