Metadata-Version: 2.4
Name: trc-8004-sdk
Version: 0.1.0b1
Summary: TRC-8004 Agent SDK for TRON - Agent identity, reputation, and validation
Author-email: sun-protocol <dev@sun.io>
License: MIT
Project-URL: Homepage, https://github.com/sun-protocol/trc-8004-sdk
Project-URL: Documentation, https://github.com/sun-protocol/trc-8004-sdk#readme
Project-URL: Repository, https://github.com/sun-protocol/trc-8004-sdk
Project-URL: Issues, https://github.com/sun-protocol/trc-8004-sdk/issues
Keywords: tron,blockchain,agent,erc-8004,trc-8004,sdk
Classifier: Development Status :: 4 - Beta
Classifier: Intended Audience :: Developers
Classifier: License :: OSI Approved :: MIT License
Classifier: Programming Language :: Python :: 3
Classifier: Programming Language :: Python :: 3.11
Classifier: Programming Language :: Python :: 3.12
Classifier: Topic :: Software Development :: Libraries :: Python Modules
Requires-Python: >=3.11
Requires-Dist: tronpy>=0.6.2
Requires-Dist: httpx>=0.27.0
Provides-Extra: dev
Requires-Dist: pytest>=8.2.0; extra == "dev"
Requires-Dist: pytest-cov>=4.0.0; extra == "dev"
Requires-Dist: ruff>=0.1.0; extra == "dev"
Requires-Dist: build>=1.0.0; extra == "dev"
Requires-Dist: twine>=5.0.0; extra == "dev"
